ds_practicals-0.1.1.dist-info/licenses/LICENSE
pandaas/__init__.py
pandaas/pract1.py
pandaas/pract10.py
pandaas/pract11.py
pandaas/pract12.py
pandaas/pract13.py
pandaas/pract2.py
pandaas/pract3.py
pandaas/pract4.py
pandaas/pract5.py
pandaas/pract6.py
pandaas/pract7.py
pandaas/pract8.py
pandaas/pract9.py
ds_practicals-0.1.1.dist-info/METADATA
ds_practicals-0.1.1.dist-info/WHEEL
ds_practicals-0.1.1.dist-info/top_level.txt
ds_practicals-0.1.1.dist-info/RECORD
